MANIFEST.in
README.md
README.rst
setup.py
pyLoadBalancer/Client.py
pyLoadBalancer/HealthCheck.py
pyLoadBalancer/LoadBalancer.py
pyLoadBalancer/StartAll.py
pyLoadBalancer/StartWorkerHub.py
pyLoadBalancer/WorkerHub.py
pyLoadBalancer/__init__.py
pyLoadBalancer/colorprint.py
pyLoadBalancer/parameters.json
pyLoadBalancer.egg-info/PKG-INFO
pyLoadBalancer.egg-info/SOURCES.txt
pyLoadBalancer.egg-info/dependency_links.txt
pyLoadBalancer.egg-info/entry_points.txt
pyLoadBalancer.egg-info/requires.txt
pyLoadBalancer.egg-info/top_level.txt
pyLoadBalancer/Monitor/MonitoringApp.py
pyLoadBalancer/Monitor/__pycache__/MonitoringApp.cpython-34.pyc
pyLoadBalancer/Monitor/__pycache__/MonitoringApp.cpython-35.pyc
pyLoadBalancer/Monitor/__pycache__/app.cpython-34.pyc
pyLoadBalancer/Monitor/static/css/jquery-ui.min.css
pyLoadBalancer/Monitor/static/css/semantic.min.css
pyLoadBalancer/Monitor/static/js/Chart.min.js
pyLoadBalancer/Monitor/static/js/jquery-3.1.0.min.js
pyLoadBalancer/Monitor/static/js/jquery-ui.min.js
pyLoadBalancer/Monitor/static/js/moment.min.js
pyLoadBalancer/Monitor/static/js/semantic.min.js
pyLoadBalancer/Monitor/static/js/stats_controller.js
pyLoadBalancer/Monitor/static/js/useful.js
pyLoadBalancer/Monitor/static/js/workers_controller.js
pyLoadBalancer/Monitor/templates/index.html
pyLoadBalancer/test/Tests.py
pyLoadBalancer/test/__init__.py
pyLoadBalancer/test/startTest.py
pyLoadBalancer/test/test_1.py
pyLoadBalancer/test/test_2.py
pyLoadBalancer/test/test_3.py
pyLoadBalancer/test/tprint.py