Metadata-Version: 1.1
Name: pyLoadBalancer
Version: 0.2.0
Summary: A load-balancer package for Python
Home-page: https://github.com/ibis-inria/pyLoadBalancer
Author: Yannick Martin - INRIA IBIS
Author-email: janiick@gmail.com
License: GPL
Download-URL: https://github.com/ibis-inria/pyLoadBalancer/archive/0.2.tar.gz
Keywords: load-balancer,multiprocessing,cluster-computing,clustering,loadbalancing,monitoring
Platform: UNKNOWN
Classifier: Development Status :: 4 - Beta
Classifier: Environment :: Console
Classifier: Environment :: Web Environment
Classifier: Intended Audience :: Science/Research
Classifier: Intended Audience :: Developers
Classifier: Intended Audience :: System Administrators
Classifier: License :: OSI Approved :: GNU General Public License v3 or later (GPLv3+)
Classifier: Natural Language :: English
Classifier: Operating System :: MacOS :: MacOS X
Classifier: Operating System :: Microsoft :: Windows
Classifier: Operating System :: POSIX
Classifier: Programming Language :: Python
Classifier: Topic :: Software Development
Classifier: Topic :: Scientific/Engineering
Classifier: Topic :: Utilities
Classifier: Topic :: System :: Hardware :: Symmetric Multi-processing
